{
    "last_updated": "2026-07-13T22:56:36.223509",
    "location": "Sakarya, Adapazarı",
    "timeline": {
        "start": "18:00",
        "end": "06:00"
    },
    "moon_phase": {
        "name": "Hilal (Son)",
        "illumination": 0,
        "angle": 354
    },
    "meteor_showers": [
        "Alpha Capricornids",
        "Delta Aquariids"
    ],
    "weather_hourly": [
        {
            "hour": "18:00",
            "cloud": 63,
            "visibility": 40520.0,
            "humidity": 54
        },
        {
            "hour": "19:00",
            "cloud": 53,
            "visibility": 40440.0,
            "humidity": 56
        },
        {
            "hour": "20:00",
            "cloud": 64,
            "visibility": 40000.0,
            "humidity": 59
        },
        {
            "hour": "21:00",
            "cloud": 14,
            "visibility": 39640.0,
            "humidity": 63
        },
        {
            "hour": "22:00",
            "cloud": 29,
            "visibility": 39020.0,
            "humidity": 67
        },
        {
            "hour": "23:00",
            "cloud": 44,
            "visibility": 37540.0,
            "humidity": 71
        },
        {
            "hour": "00:00",
            "cloud": 54,
            "visibility": 35760.0,
            "humidity": 74
        },
        {
            "hour": "01:00",
            "cloud": 59,
            "visibility": 33500.0,
            "humidity": 77
        },
        {
            "hour": "02:00",
            "cloud": 63,
            "visibility": 28640.0,
            "humidity": 83
        },
        {
            "hour": "03:00",
            "cloud": 95,
            "visibility": 20800.0,
            "humidity": 89
        },
        {
            "hour": "04:00",
            "cloud": 96,
            "visibility": 18040.0,
            "humidity": 92
        },
        {
            "hour": "05:00",
            "cloud": 73,
            "visibility": 19320.0,
            "humidity": 92
        },
        {
            "hour": "06:00",
            "cloud": 78,
            "visibility": 18800.0,
            "humidity": 91
        }
    ],
    "objects": [
        {
            "name": "Ay",
            "type": "moon",
            "rise": "06:32",
            "set": "20:52",
            "visible": true,
            "altitude_graph": [
                19.6,
                9.4,
                0.1,
                -8.3,
                -15.3,
                -20.4,
                -23.3,
                -23.6,
                -21.4,
                -16.8,
                -10.3,
                -2.3,
                6.9
            ],
            "distance_km": "361.863"
        },
        {
            "name": "Merkür",
            "type": "planet",
            "rise": "05:42",
            "set": "19:55",
            "visible": true,
            "altitude_graph": [
                21.8,
                10.5,
                -0.3,
                -10.3,
                -19.2,
                -26.2,
                -30.7,
                -32.1,
                -30.2,
                -25.3,
                -18.0,
                -8.9,
                1.3
            ],
            "distance_km": "86.223.962"
        },
        {
            "name": "Venüs",
            "type": "planet",
            "rise": "09:20",
            "set": "22:39",
            "visible": true,
            "altitude_graph": [
                50.2,
                40.5,
                29.6,
                18.4,
                7.0,
                -4.0,
                -14.5,
                -23.8,
                -31.4,
                -36.5,
                -38.3,
                -36.5,
                -31.3
            ],
            "distance_km": "141.231.651"
        },
        {
            "name": "Mars",
            "type": "planet",
            "rise": "02:41",
            "set": "17:31",
            "visible": true,
            "altitude_graph": [
                -5.0,
                -13.7,
                -20.7,
                -25.4,
                -27.3,
                -26.2,
                -22.1,
                -15.7,
                -7.4,
                2.3,
                12.7,
                23.8,
                35.1
            ],
            "distance_km": "308.983.275"
        },
        {
            "name": "Jüpiter",
            "type": "planet",
            "rise": "06:33",
            "set": "21:06",
            "visible": true,
            "altitude_graph": [
                34.2,
                22.8,
                11.7,
                1.1,
                -8.7,
                -17.2,
                -23.9,
                -28.1,
                -29.3,
                -27.3,
                -22.5,
                -15.3,
                -6.5
            ],
            "distance_km": "938.408.287"
        },
        {
            "name": "Satürn",
            "type": "planet",
            "rise": "00:10",
            "set": "12:42",
            "visible": true,
            "altitude_graph": [
                -45.2,
                -45.2,
                -41.2,
                -34.0,
                -24.8,
                -14.3,
                -3.2,
                8.2,
                19.4,
                30.2,
                40.0,
                47.8,
                52.2
            ],
            "distance_km": "1.388.748.350"
        }
    ],
    "iss_passes": [
        {
            "start": "02:48",
            "max_elev": 14,
            "end": "02:52"
        },
        {
            "start": "17:50",
            "max_elev": 20,
            "end": "17:55"
        },
        {
            "start": "19:25",
            "max_elev": 43,
            "end": "19:31"
        },
        {
            "start": "21:03",
            "max_elev": 14,
            "end": "21:07"
        },
        {
            "start": "22:41",
            "max_elev": 13,
            "end": "22:44"
        },
        {
            "start": "00:17",
            "max_elev": 34,
            "end": "00:23"
        }
    ],
    "lists": {
        "naked_eye": [
            {
                "name": "Jüpiter",
                "mag": -2.8
            },
            {
                "name": "Sirius",
                "mag": -1.4
            },
            {
                "name": "Pleiades (M45)",
                "mag": 1.6
            },
            {
                "name": "Andromeda (M31)",
                "mag": 3.4
            },
            {
                "name": "Betelgeuse",
                "mag": 0.5
            }
        ],
        "binocular": [
            {
                "name": "Orion Bulutsusu (M42)",
                "mag": 4.0
            },
            {
                "name": "Arı Kovanı (M44)",
                "mag": 3.7
            },
            {
                "name": "Herkül Kümesi (M13)",
                "mag": 5.8
            },
            {
                "name": "Çift Küme (NGC 869)",
                "mag": 3.7
            }
        ]
    }
}